<?xml version="1.0" encoding="UTF-8"?>
<entity-mappings version="2.2"
                 xmlns="http://xmlns.jcp.org/xml/ns/persistence/orm"
                 xmlns:xsi="http://www.w3.org/2001/XMLSchema-instance"
                 xsi:schemaLocation="http://xmlns.jcp.org/xml/ns/persistence/orm http://xmlns.jcp.org/xml/ns/persistence/orm_2_2.xsd">

    <entity class="io.roadmaps.core.domain.model.module.Module" name="Module">
        <table name="modules" />
        <attributes>
            <id name="id">
                <column name="id" />
            </id>
            <basic name="title">
                <column name="title" />
            </basic>
            <basic name="courseId">
                <column name="course_id" />
            </basic>

            <!-- TODO: !!!EAGER FETCH!!! Make it lazy and make code that uses this field transactional before go to prod!-->
            <one-to-many name="leaves" target-entity="io.roadmaps.core.domain.model.leaf.Leaf" fetch="EAGER" orphan-removal="true">
                <order-column name="order_id" nullable="false" />
                <join-column name="module_id" />
                <cascade>
                    <cascade-all/>
                </cascade>
            </one-to-many>
        </attributes>
    </entity>
</entity-mappings>
